.gitignore
CHANGES.rst
README.rst
setup.cfg
setup.py
minbool/__init__.py
minbool/astgen.py
minbool/codegen.py
minbool/tests.py
minbool.egg-info/PKG-INFO
minbool.egg-info/SOURCES.txt
minbool.egg-info/dependency_links.txt
minbool.egg-info/entry_points.txt
minbool.egg-info/not-zip-safe
minbool.egg-info/requires.txt
minbool.egg-info/top_level.txt