Metadata-Version: 1.1
Name: minbool
Version: 1.0
Summary: Implementation of Quine-McCluskey algorithm for minimizing boolean expressions.
Home-page: UNKNOWN
Author: Chris Rossi
Author-email: chris@archimedeanco.com
License: UNKNOWN
Platform: UNKNOWN
Classifier: Intended Audience :: Developers
Classifier: Programming Language :: Python
